{
	"configurations" : 
	[
		{
			"directories" : 
			[
				{
					"build" : ".",
					"jsonFile" : "directory-.-Debug-f5ebdc15457944623624.json",
					"minimumCMakeVersion" : 
					{
						"string" : "3.25"
					},
					"projectIndex" : 0,
					"source" : ".",
					"targetIndexes" : 
					[
						0
					]
				}
			],
			"name" : "Debug",
			"projects" : 
			[
				{
					"directoryIndexes" : 
					[
						0
					],
					"name" : "code_stack_amazon",
					"targetIndexes" : 
					[
						0
					]
				}
			],
			"targets" : 
			[
				{
					"directoryIndex" : 0,
					"id" : "code_stack_amazon::@6890427a1f51a3e7e1df",
					"jsonFile" : "target-code_stack_amazon-Debug-d0e5b6223074aec440ae.json",
					"name" : "code_stack_amazon",
					"projectIndex" : 0
				}
			]
		}
	],
	"kind" : "codemodel",
	"paths" : 
	{
		"build" : "/home/just/Personal/unistuff/ASD/lab/code_stack_amazon/cmake-build-debug",
		"source" : "/home/just/Personal/unistuff/ASD/lab/code_stack_amazon"
	},
	"version" : 
	{
		"major" : 2,
		"minor" : 4
	}
}
